eb_contracts/__init__.py
eb_contracts/api/__init__.py
eb_contracts/api/migrate_forecast.py
eb_contracts/api/validate.py
eb_contracts/contracts/__init__.py
eb_contracts/contracts/_internal/__init__.py
eb_contracts/contracts/_internal/runtime.py
eb_contracts/contracts/_internal/typing.py
eb_contracts/contracts/context/__init__.py
eb_contracts/contracts/context/v1/__init__.py
eb_contracts/contracts/context/v1/run_context.py
eb_contracts/contracts/costs/__init__.py
eb_contracts/contracts/costs/v1/__init__.py
eb_contracts/contracts/costs/v1/cost_asymmetry_spec.py
eb_contracts/contracts/demand_panel/__init__.py
eb_contracts/contracts/demand_panel/v1/__init__.py
eb_contracts/contracts/demand_panel/v1/panel_demand.py
eb_contracts/contracts/forecast_panel/__init__.py
eb_contracts/contracts/forecast_panel/v1/__init__.py
eb_contracts/contracts/forecast_panel/v1/forecast_panel.py
eb_contracts/contracts/readiness/v1/__init__.py
eb_contracts/contracts/readiness/v1/panel_fpc_result.py
eb_contracts/contracts/results/__init__.py
eb_contracts/contracts/results/v1/__init__.py
eb_contracts/contracts/results/v1/panel_point_result.py
eb_contracts/definitions/__init__.py
eb_contracts/definitions/conventions.py
eb_contracts/definitions/glossary.py
eb_contracts/definitions/semantics.py
eb_contracts/definitions/units.py
eb_contracts/validation/errors.py
eb_contracts-0.2.2.dist-info/METADATA
eb_contracts-0.2.2.dist-info/WHEEL
eb_contracts-0.2.2.dist-info/licenses/LICENSE
eb_contracts-0.2.2.dist-info/RECORD
