Metadata-Version: 2.4
Name: eb-contracts
Version: 0.2.2
Summary: Electric Barometer data contracts and validation utilities.
Project-URL: Homepage, https://github.com/Economistician/eb-contracts
Project-URL: Repository, https://github.com/Economistician/eb-contracts
Project-URL: Issues, https://github.com/Economistician/eb-contracts/issues
Author: Electric Barometer
License: BSD-3-Clause
License-File: LICENSE
Keywords: data-contracts,electric-barometer,forecasting,validation
Classifier: Development Status :: 3 - Alpha
Classifier: Intended Audience :: Science/Research
Classifier: License :: OSI Approved :: BSD License
Classifier: Programming Language :: Python :: 3
Classifier: Programming Language :: Python :: 3 :: Only
Classifier: Programming Language :: Python :: 3.11
Classifier: Programming Language :: Python :: 3.12
Classifier: Programming Language :: Python :: 3.13
Requires-Python: >=3.11
Requires-Dist: pandas>=2.0
Provides-Extra: dev
Requires-Dist: pre-commit>=3.7; extra == 'dev'
Requires-Dist: pyright>=1.1.380; extra == 'dev'
Requires-Dist: pytest>=8; extra == 'dev'
Requires-Dist: ruff>=0.6; extra == 'dev'
Provides-Extra: docs
Requires-Dist: mkdocs-material>=9.5; extra == 'docs'
Requires-Dist: mkdocs>=1.6; extra == 'docs'
Provides-Extra: test
Requires-Dist: pytest>=8; extra == 'test'
